lab5/carrySaveAdder.v
module fullAdder (a, b, cin, sum, ca);

    input a, b, cin;
    output sum, ca;

    wire w1, w2, w3, w4, w5;

    xor xor_0 (w1, a, b);
    xor xor_1 (sum, w1, cin);

    and and_0 (w2, a, b);
    and and_1 (w3, a, cin);
    and and_2 (w4, b, cin);
    or  or_0 (w5, w2, w3);
    or  or_1 (ca, w4, w5);

endmodule

module carrySaveAdder (X, Y, Z, S, C);
    input [63:0] X, Y, Z;
    output [63:0] S, C;

    assign C[0] = 1'b0;

    genvar i;

    generate
        for(i = 0; i < 63; i = i + 1)
        begin: full_adder
            fullAdder fa(X[i], Y[i], Z[i], S[i], C[i + 1]);
        end
    endgenerate

    assign S[63] = 1'b0;

endmodule

lab2/fourBitAdder.v
`include "fullAdderGate.v"

module fourBitAdder (a, b, cin, sum, ca);
input [3:0] a, b;
input cin;

output [3:0] sum;
output ca;

wire c1, c2, c3;

fullAdder FA_0 (a[0], b[0], cin, sum[0], c1);
fullAdder FA_1 (a[1], b[1], c1, sum[1], c2);
fullAdder FA_2 (a[2], b[2], c2, sum[2], c3);
fullAdder FA_3 (a[3], b[3], c3, sum[3], ca);

endmodule

lab2/eightBitAdder.v
`include "fourBitAdder.v"

module eightBitAdder(a, b, cin, sum, ca);
input [7:0] a, b;
input cin;

output [7:0] sum;
output ca;

wire c1;

fourBitAdder FBA_0(a[3:0], b[3:0], cin, sum[3:0], c1);
fourBitAdder FBA_1(a[7:4], b[7:4], c1, sum[7:4], ca);

endmodule

lab2/sixteenBitAdder.v
`include "eightBitAdder.v"

module sixteenBitAdder(a, b, cin, sum, ca);
input [15:0] a, b;
input cin;

output [15:0] sum;
output ca;

wire c1;

eightBitAdder EBA_0(a[7:0], b[7:0], cin, sum[7:0], c1);
eightBitAdder EBA_1(a[15:8], b[15:8], c1, sum[15:8], ca);

endmodule

lab2/thirtyTwoBitAdder.v
`include "sixteenBitAdder.v"

module thirtyTwoBitAdder(a, b, cin, sum, ca);
input [31:0] a, b;
input cin;

output [31:0] sum;
output ca;

wire c1;

sixteenBitAdder EBA_0(a[15:0], b[15:0], cin, sum[15:0], c1);
sixteenBitAdder EBA_1(a[31:16], b[31:16], c1, sum[31:16], ca);

endmodule

lab2/thirtyTwoBitAdder_tb.v
`include "thirtyTwoBitAdder.v"

module top;
reg [31:0] a, b;
reg cin;
wire [31:0] sum;
wire ca;

thirtyTwoBitAdder FullAdd_0 (a, b, cin, sum, ca);

initial
begin
	$dumpfile("output.vcd");
	$dumpvars(0, top);
	#1 a = 32'b0000_0000_0000_0000_0000_0000_0000_0000;
	#1 b = 32'b0000_0000_0000_0000_0000_0000_0000_0000;
	#1 cin = 1'b0;
	#1 a = 32'b1111_1111_1111_1111_1111_1111_1111_1111;
	#1 b = 32'b1111_1111_1111_1111_1111_1111_1111_1111;
	#1 cin = 1'b1;
	#1 b = 32'b1010_1010_1010_1010_1010_1010_1010_1010;
end

initial
	$monitor ($time, "  a = %b; b = %b; cin = %b; sum = %b; ca = %b", a, b, cin, sum, ca);

endmodule

lab2/output.vcd
$date
	Thu Aug 20 16:45:02 2020
$end
$version
	Icarus Verilog
$end
$timescale
	1s
$end
$scope module top $end
$var wire 32 ! sum [31:0] $end
$var wire 1 " ca $end
$var reg 32 # a [31:0] $end
$var reg 32 $ b [31:0] $end
$var reg 1 % cin $end
$scope module FullAdd_0 $end
$var wire 32 & a [31:0] $end
$var wire 32 ' b [31:0] $end
$var wire 1 % cin $end
$var wire 32 ( sum [31:0] $end
$var wire 1 " ca $end
$var wire 1 ) c1 $end
$scope module EBA_0 $end
$var wire 16 * a [15:0] $end
$var wire 16 + b [15:0] $end
$var wire 1 % cin $end
$var wire 16 , sum [15:0] $end
$var wire 1 ) ca $end
$var wire 1 - c1 $end
$scope module EBA_0 $end
$var wire 8 . a [7:0] $end
$var wire 8 / b [7:0] $end
$var wire 1 % cin $end
$var wire 8 0 sum [7:0] $end
$var wire 1 - ca $end
$var wire 1 1 c1 $end
$scope module FBA_0 $end
$var wire 4 2 a [3:0] $end
$var wire 4 3 b [3:0] $end
$var wire 1 % cin $end
$var wire 4 4 sum [3:0] $end
$var wire 1 1 ca $end
$var wire 1 5 c3 $end
$var wire 1 6 c2 $end
$var wire 1 7 c1 $end
$scope module FA_0 $end
$var wire 1 8 a $end
$var wire 1 9 b $end
$var wire 1 7 ca $end
$var wire 1 % cin $end
$var wire 1 : sum $end
$var wire 1 ; w1 $end
$var wire 1 < w2 $end
$var wire 1 = w3 $end
$var wire 1 > w4 $end
$var wire 1 ? w5 $end
$upscope $end
$scope module FA_1 $end
$var wire 1 @ a $end
$var wire 1 A b $end
$var wire 1 6 ca $end
$var wire 1 7 cin $end
$var wire 1 B sum $end
$var wire 1 C w1 $end
$var wire 1 D w2 $end
$var wire 1 E w3 $end
$var wire 1 F w4 $end
$var wire 1 G w5 $end
$upscope $end
$scope module FA_2 $end
$var wire 1 H a $end
$var wire 1 I b $end
$var wire 1 5 ca $end
$var wire 1 6 cin $end
$var wire 1 J sum $end
$var wire 1 K w1 $end
$var wire 1 L w2 $end
$var wire 1 M w3 $end
$var wire 1 N w4 $end
$var wire 1 O w5 $end
$upscope $end
$scope module FA_3 $end
$var wire 1 P a $end
$var wire 1 Q b $end
$var wire 1 1 ca $end
$var wire 1 5 cin $end
$var wire 1 R sum $end
$var wire 1 S w1 $end
$var wire 1 T w2 $end
$var wire 1 U w3 $end
$var wire 1 V w4 $end
$var wire 1 W w5 $end
$upscope $end
$upscope $end
$scope module FBA_1 $end
$var wire 4 X a [3:0] $end
$var wire 4 Y b [3:0] $end
$var wire 1 1 cin $end
$var wire 4 Z sum [3:0] $end
$var wire 1 - ca $end
$var wire 1 [ c3 $end
$var wire 1 \ c2 $end
$var wire 1 ] c1 $end
$scope module FA_0 $end
$var wire 1 ^ a $end
$var wire 1 _ b $end
$var wire 1 ] ca $end
$var wire 1 1 cin $end
$var wire 1 ` sum $end
$var wire 1 a w1 $end
$var wire 1 b w2 $end
$var wire 1 c w3 $end
$var wire 1 d w4 $end
$var wire 1 e w5 $end
$upscope $end
$scope module FA_1 $end
$var wire 1 f a $end
$var wire 1 g b $end
$var wire 1 \ ca $end
$var wire 1 ] cin $end
$var wire 1 h sum $end
$var wire 1 i w1 $end
$var wire 1 j w2 $end
$var wire 1 k w3 $end
$var wire 1 l w4 $end
$var wire 1 m w5 $end
$upscope $end
$scope module FA_2 $end
$var wire 1 n a $end
$var wire 1 o b $end
$var wire 1 [ ca $end
$var wire 1 \ cin $end
$var wire 1 p sum $end
$var wire 1 q w1 $end
$var wire 1 r w2 $end
$var wire 1 s w3 $end
$var wire 1 t w4 $end
$var wire 1 u w5 $end
$upscope $end
$scope module FA_3 $end
$var wire 1 v a $end
$var wire 1 w b $end
$var wire 1 - ca $end
$var wire 1 [ cin $end
$var wire 1 x sum $end
$var wire 1 y w1 $end
$var wire 1 z w2 $end
$var wire 1 { w3 $end
$var wire 1 | w4 $end
$var wire 1 } w5 $end
$upscope $end
$upscope $end
$upscope $end
$scope module EBA_1 $end
$var wire 8 ~ a [7:0] $end
$var wire 8 !" b [7:0] $end
$var wire 1 - cin $end
$var wire 8 "" sum [7:0] $end
$var wire 1 ) ca $end
$var wire 1 #" c1 $end
$scope module FBA_0 $end
$var wire 4 $" a [3:0] $end
$var wire 4 %" b [3:0] $end
$var wire 1 - cin $end
$var wire 4 &" sum [3:0] $end
$var wire 1 #" ca $end
$var wire 1 '" c3 $end
$var wire 1 (" c2 $end
$var wire 1 )" c1 $end
$scope module FA_0 $end
$var wire 1 *" a $end
$var wire 1 +" b $end
$var wire 1 )" ca $end
$var wire 1 - cin $end
$var wire 1 ," sum $end
$var wire 1 -" w1 $end
$var wire 1 ." w2 $end
$var wire 1 /" w3 $end
$var wire 1 0" w4 $end
$var wire 1 1" w5 $end
$upscope $end
$scope module FA_1 $end
$var wire 1 2" a $end
$var wire 1 3" b $end
$var wire 1 (" ca $end
$var wire 1 )" cin $end
$var wire 1 4" sum $end
$var wire 1 5" w1 $end
$var wire 1 6" w2 $end
$var wire 1 7" w3 $end
$var wire 1 8" w4 $end
$var wire 1 9" w5 $end
$upscope $end
$scope module FA_2 $end
$var wire 1 :" a $end
$var wire 1 ;" b $end
$var wire 1 '" ca $end
$var wire 1 (" cin $end
$var wire 1 <" sum $end
$var wire 1 =" w1 $end
$var wire 1 >" w2 $end
$var wire 1 ?" w3 $end
$var wire 1 @" w4 $end
$var wire 1 A" w5 $end
$upscope $end
$scope module FA_3 $end
$var wire 1 B" a $end
$var wire 1 C" b $end
$var wire 1 #" ca $end
$var wire 1 '" cin $end
$var wire 1 D" sum $end
$var wire 1 E" w1 $end
$var wire 1 F" w2 $end
$var wire 1 G" w3 $end
$var wire 1 H" w4 $end
$var wire 1 I" w5 $end
$upscope $end
$upscope $end
$scope module FBA_1 $end
$var wire 4 J" a [3:0] $end
$var wire 4 K" b [3:0] $end
$var wire 1 #" cin $end
$var wire 4 L" sum [3:0] $end
$var wire 1 ) ca $end
$var wire 1 M" c3 $end
$var wire 1 N" c2 $end
$var wire 1 O" c1 $end
$scope module FA_0 $end
$var wire 1 P" a $end
$var wire 1 Q" b $end
$var wire 1 O" ca $end
$var wire 1 #" cin $end
$var wire 1 R" sum $end
$var wire 1 S" w1 $end
$var wire 1 T" w2 $end
$var wire 1 U" w3 $end
$var wire 1 V" w4 $end
$var wire 1 W" w5 $end
$upscope $end
$scope module FA_1 $end
$var wire 1 X" a $end
$var wire 1 Y" b $end
$var wire 1 N" ca $end
$var wire 1 O" cin $end
$var wire 1 Z" sum $end
$var wire 1 [" w1 $end
$var wire 1 \" w2 $end
$var wire 1 ]" w3 $end
$var wire 1 ^" w4 $end
$var wire 1 _" w5 $end
$upscope $end
$scope module FA_2 $end
$var wire 1 `" a $end
$var wire 1 a" b $end
$var wire 1 M" ca $end
$var wire 1 N" cin $end
$var wire 1 b" sum $end
$var wire 1 c" w1 $end
$var wire 1 d" w2 $end
$var wire 1 e" w3 $end
$var wire 1 f" w4 $end
$var wire 1 g" w5 $end
$upscope $end
$scope module FA_3 $end
$var wire 1 h" a $end
$var wire 1 i" b $end
$var wire 1 ) ca $end
$var wire 1 M" cin $end
$var wire 1 j" sum $end
$var wire 1 k" w1 $end
$var wire 1 l" w2 $end
$var wire 1 m" w3 $end
$var wire 1 n" w4 $end
$var wire 1 o" w5 $end
$upscope $end
$upscope $end
$upscope $end
$upscope $end
$scope module EBA_1 $end
$var wire 16 p" a [15:0] $end
$var wire 16 q" b [15:0] $end
$var wire 1 ) cin $end
$var wire 16 r" sum [15:0] $end
$var wire 1 " ca $end
$var wire 1 s" c1 $end
$scope module EBA_0 $end
$var wire 8 t" a [7:0] $end
$var wire 8 u" b [7:0] $end
$var wire 1 ) cin $end
$var wire 8 v" sum [7:0] $end
$var wire 1 s" ca $end
$var wire 1 w" c1 $end
$scope module FBA_0 $end
$var wire 4 x" a [3:0] $end
$var wire 4 y" b [3:0] $end
$var wire 1 ) cin $end
$var wire 4 z" sum [3:0] $end
$var wire 1 w" ca $end
$var wire 1 {" c3 $end
$var wire 1 |" c2 $end
$var wire 1 }" c1 $end
$scope module FA_0 $end
$var wire 1 ~" a $end
$var wire 1 !# b $end
$var wire 1 }" ca $end
$var wire 1 ) cin $end
$var wire 1 "# sum $end
$var wire 1 ## w1 $end
$var wire 1 $# w2 $end
$var wire 1 %# w3 $end
$var wire 1 &# w4 $end
$var wire 1 '# w5 $end
$upscope $end
$scope module FA_1 $end
$var wire 1 (# a $end
$var wire 1 )# b $end
$var wire 1 |" ca $end
$var wire 1 }" cin $end
$var wire 1 *# sum $end
$var wire 1 +# w1 $end
$var wire 1 ,# w2 $end
$var wire 1 -# w3 $end
$var wire 1 .# w4 $end
$var wire 1 /# w5 $end
$upscope $end
$scope module FA_2 $end
$var wire 1 0# a $end
$var wire 1 1# b $end
$var wire 1 {" ca $end
$var wire 1 |" cin $end
$var wire 1 2# sum $end
$var wire 1 3# w1 $end
$var wire 1 4# w2 $end
$var wire 1 5# w3 $end
$var wire 1 6# w4 $end
$var wire 1 7# w5 $end
$upscope $end
$scope module FA_3 $end
$var wire 1 8# a $end
$var wire 1 9# b $end
$var wire 1 w" ca $end
$var wire 1 {" cin $end
$var wire 1 :# sum $end
$var wire 1 ;# w1 $end
$var wire 1 <# w2 $end
$var wire 1 =# w3 $end
$var wire 1 ># w4 $end
$var wire 1 ?# w5 $end
$upscope $end
$upscope $end
$scope module FBA_1 $end
$var wire 4 @# a [3:0] $end
$var wire 4 A# b [3:0] $end
$var wire 1 w" cin $end
$var wire 4 B# sum [3:0] $end
$var wire 1 s" ca $end
$var wire 1 C# c3 $end
$var wire 1 D# c2 $end
$var wire 1 E# c1 $end
$scope module FA_0 $end
$var wire 1 F# a $end
$var wire 1 G# b $end
$var wire 1 E# ca $end
$var wire 1 w" cin $end
$var wire 1 H# sum $end
$var wire 1 I# w1 $end
$var wire 1 J# w2 $end
$var wire 1 K# w3 $end
$var wire 1 L# w4 $end
$var wire 1 M# w5 $end
$upscope $end
$scope module FA_1 $end
$var wire 1 N# a $end
$var wire 1 O# b $end
$var wire 1 D# ca $end
$var wire 1 E# cin $end
$var wire 1 P# sum $end
$var wire 1 Q# w1 $end
$var wire 1 R# w2 $end
$var wire 1 S# w3 $end
$var wire 1 T# w4 $end
$var wire 1 U# w5 $end
$upscope $end
$scope module FA_2 $end
$var wire 1 V# a $end
$var wire 1 W# b $end
$var wire 1 C# ca $end
$var wire 1 D# cin $end
$var wire 1 X# sum $end
$var wire 1 Y# w1 $end
$var wire 1 Z# w2 $end
$var wire 1 [# w3 $end
$var wire 1 \# w4 $end
$var wire 1 ]# w5 $end
$upscope $end
$scope module FA_3 $end
$var wire 1 ^# a $end
$var wire 1 _# b $end
$var wire 1 s" ca $end
$var wire 1 C# cin $end
$var wire 1 `# sum $end
$var wire 1 a# w1 $end
$var wire 1 b# w2 $end
$var wire 1 c# w3 $end
$var wire 1 d# w4 $end
$var wire 1 e# w5 $end
$upscope $end
$upscope $end
$upscope $end
$scope module EBA_1 $end
$var wire 8 f# a [7:0] $end
$var wire 8 g# b [7:0] $end
$var wire 1 s" cin $end
$var wire 8 h# sum [7:0] $end
$var wire 1 " ca $end
$var wire 1 i# c1 $end
$scope module FBA_0 $end
$var wire 4 j# a [3:0] $end
$var wire 4 k# b [3:0] $end
$var wire 1 s" cin $end
$var wire 4 l# sum [3:0] $end
$var wire 1 i# ca $end
$var wire 1 m# c3 $end
$var wire 1 n# c2 $end
$var wire 1 o# c1 $end
$scope module FA_0 $end
$var wire 1 p# a $end
$var wire 1 q# b $end
$var wire 1 o# ca $end
$var wire 1 s" cin $end
$var wire 1 r# sum $end
$var wire 1 s# w1 $end
$var wire 1 t# w2 $end
$var wire 1 u# w3 $end
$var wire 1 v# w4 $end
$var wire 1 w# w5 $end
$upscope $end
$scope module FA_1 $end
$var wire 1 x# a $end
$var wire 1 y# b $end
$var wire 1 n# ca $end
$var wire 1 o# cin $end
$var wire 1 z# sum $end
$var wire 1 {# w1 $end
$var wire 1 |# w2 $end
$var wire 1 }# w3 $end
$var wire 1 ~# w4 $end
$var wire 1 !$ w5 $end
$upscope $end
$scope module FA_2 $end
$var wire 1 "$ a $end
$var wire 1 #$ b $end
$var wire 1 m# ca $end
$var wire 1 n# cin $end
$var wire 1 $$ sum $end
$var wire 1 %$ w1 $end
$var wire 1 &$ w2 $end
$var wire 1 '$ w3 $end
$var wire 1 ($ w4 $end
$var wire 1 )$ w5 $end
$upscope $end
$scope module FA_3 $end
$var wire 1 *$ a $end
$var wire 1 +$ b $end
$var wire 1 i# ca $end
$var wire 1 m# cin $end
$var wire 1 ,$ sum $end
$var wire 1 -$ w1 $end
$var wire 1 .$ w2 $end
$var wire 1 /$ w3 $end
$var wire 1 0$ w4 $end
$var wire 1 1$ w5 $end
$upscope $end
$upscope $end
$scope module FBA_1 $end
$var wire 4 2$ a [3:0] $end
$var wire 4 3$ b [3:0] $end
$var wire 1 i# cin $end
$var wire 4 4$ sum [3:0] $end
$var wire 1 " ca $end
$var wire 1 5$ c3 $end
$var wire 1 6$ c2 $end
$var wire 1 7$ c1 $end
$scope module FA_0 $end
$var wire 1 8$ a $end
$var wire 1 9$ b $end
$var wire 1 7$ ca $end
$var wire 1 i# cin $end
$var wire 1 :$ sum $end
$var wire 1 ;$ w1 $end
$var wire 1 <$ w2 $end
$var wire 1 =$ w3 $end
$var wire 1 >$ w4 $end
$var wire 1 ?$ w5 $end
$upscope $end
$scope module FA_1 $end
$var wire 1 @$ a $end
$var wire 1 A$ b $end
$var wire 1 6$ ca $end
$var wire 1 7$ cin $end
$var wire 1 B$ sum $end
$var wire 1 C$ w1 $end
$var wire 1 D$ w2 $end
$var wire 1 E$ w3 $end
$var wire 1 F$ w4 $end
$var wire 1 G$ w5 $end
$upscope $end
$scope module FA_2 $end
$var wire 1 H$ a $end
$var wire 1 I$ b $end
$var wire 1 5$ ca $end
$var wire 1 6$ cin $end
$var wire 1 J$ sum $end
$var wire 1 K$ w1 $end
$var wire 1 L$ w2 $end
$var wire 1 M$ w3 $end
$var wire 1 N$ w4 $end
$var wire 1 O$ w5 $end
$upscope $end
$scope module FA_3 $end
$var wire 1 P$ a $end
$var wire 1 Q$ b $end
$var wire 1 " ca $end
$var wire 1 5$ cin $end
$var wire 1 R$ sum $end
$var wire 1 S$ w1 $end
$var wire 1 T$ w2 $end
$var wire 1 U$ w3 $end
$var wire 1 V$ w4 $end
$var wire 1 W$ w5 $end
$upscope $end
$upscope $end
$upscope $end
$upscope $end
$upscope $end
$upscope $end
$enddefinitions $end
#0
$dumpvars
xW$
xV$
xU$
xT$
xS$
xR$
xQ$
xP$
xO$
xN$
xM$
xL$
xK$
xJ$
xI$
xH$
xG$
xF$
xE$
xD$
xC$
xB$
xA$
x@$
x?$
x>$
x=$
x<$
x;$
x:$
x9$
x8$
x7$
x6$
x5$
bx 4$
bx 3$
bx 2$
x1$
x0$
x/$
x.$
x-$
x,$
x+$
x*$
x)$
x($
x'$
x&$
x%$
x$$
x#$
x"$
x!$
x~#
x}#
x|#
x{#
xz#
xy#
xx#
xw#
xv#
xu#
xt#
xs#
xr#
xq#
xp#
xo#
xn#
xm#
bx l#
bx k#
bx j#
xi#
bx h#
bx g#
bx f#
xe#
xd#
xc#
xb#
xa#
x`#
x_#
x^#
x]#
x\#
x[#
xZ#
xY#
xX#
xW#
xV#
xU#
xT#
xS#
xR#
xQ#
xP#
xO#
xN#
xM#
xL#
xK#
xJ#
xI#
xH#
xG#
xF#
xE#
xD#
xC#
bx B#
bx A#
bx @#
x?#
x>#
x=#
x<#
x;#
x:#
x9#
x8#
x7#
x6#
x5#
x4#
x3#
x2#
x1#
x0#
x/#
x.#
x-#
x,#
x+#
x*#
x)#
x(#
x'#
x&#
x%#
x$#
x##
x"#
x!#
x~"
x}"
x|"
x{"
bx z"
bx y"
bx x"
xw"
bx v"
bx u"
bx t"
xs"
bx r"
bx q"
bx p"
xo"
xn"
xm"
xl"
xk"
xj"
xi"
xh"
xg"
xf"
xe"
xd"
xc"
xb"
xa"
x`"
x_"
x^"
x]"
x\"
x["
xZ"
xY"
xX"
xW"
xV"
xU"
xT"
xS"
xR"
xQ"
xP"
xO"
xN"
xM"
bx L"
bx K"
bx J"
xI"
xH"
xG"
xF"
xE"
xD"
xC"
xB"
xA"
x@"
x?"
x>"
x="
x<"
x;"
x:"
x9"
x8"
x7"
x6"
x5"
x4"
x3"
x2"
x1"
x0"
x/"
x."
x-"
x,"
x+"
x*"
x)"
x("
x'"
bx &"
bx %"
bx $"
x#"
bx ""
bx !"
bx ~
x}
x|
x{
xz
xy
xx
xw
xv
xu
xt
xs
xr
xq
xp
xo
xn
xm
xl
xk
xj
xi
xh
xg
xf
xe
xd
xc
xb
xa
x`
x_
x^
x]
x\
x[
bx Z
bx Y
bx X
xW
xV
xU
xT
xS
xR
xQ
xP
xO
xN
xM
xL
xK
xJ
xI
xH
xG
xF
xE
xD
xC
xB
xA
x@
x?
x>
x=
x<
x;
x:
x9
x8
x7
x6
x5
bx 4
bx 3
bx 2
x1
bx 0
bx /
bx .
x-
bx ,
bx +
bx *
x)
bx (
bx '
bx &
x%
bx $
bx #
x"
bx !
$end
#1
0?
0G
0O
0W
0e
0m
0u
0}
01"
09"
0A"
0I"
0W"
0_"
0g"
0o"
0'#
0/#
07#
0?#
0M#
0U#
0]#
0e#
0w#
0!$
0)$
01$
0?$
0G$
0O$
0W$
0<
0=
0D
0E
0L
0M
0T
0U
0b
0c
0j
0k
0r
0s
0z
0{
0."
0/"
06"
07"
0>"
0?"
0F"
0G"
0T"
0U"
0\"
0]"
0d"
0e"
0l"
0m"
0$#
0%#
0,#
0-#
04#
05#
0<#
0=#
0J#
0K#
0R#
0S#
0Z#
0[#
0b#
0c#
0t#
0u#
0|#
0}#
0&$
0'$
0.$
0/$
0<$
0=$
0D$
0E$
0L$
0M$
0T$
0U$
08
0@
0H
0P
0^
0f
0n
0v
0*"
02"
0:"
0B"
0P"
0X"
0`"
0h"
0~"
0(#
00#
08#
0F#
0N#
0V#
0^#
0p#
0x#
0"$
0*$
08$
0@$
0H$
0P$
b0 2
b0 X
b0 $"
b0 J"
b0 x"
b0 @#
b0 j#
b0 2$
b0 .
b0 ~
b0 t"
b0 f#
b0 *
b0 p"
b0 #
b0 &
#2
0B
0J
b0x 4
0R
0`
0h
0p
b0x 0
b0 Z
0x
0,"
04"
0<"
b0 &"
0D"
0R"
0Z"
0b"
b0x ,
b0 ""
b0 L"
0j"
0"#
0*#
02#
b0 z"
0:#
0H#
0P#
0X#
b0 v"
b0 B#
0`#
0r#
0z#
0$$
b0 l#
0,$
0:$
0B$
0J$
b0x !
b0x (
b0 r"
b0 h#
b0 4$
0R$
07
06
05
01
0]
0\
0[
0-
0)"
0("
0'"
0#"
0O"
0N"
0M"
0)
0}"
0|"
0{"
0w"
0E#
0D#
0C#
0s"
0o#
0n#
0m#
0i#
07$
06$
05$
0"
0;
0>
0C
0F
0K
0N
0S
0V
0a
0d
0i
0l
0q
0t
0y
0|
0-"
00"
05"
08"
0="
0@"
0E"
0H"
0S"
0V"
0["
0^"
0c"
0f"
0k"
0n"
0##
0&#
0+#
0.#
03#
06#
0;#
0>#
0I#
0L#
0Q#
0T#
0Y#
0\#
0a#
0d#
0s#
0v#
0{#
0~#
0%$
0($
0-$
00$
0;$
0>$
0C$
0F$
0K$
0N$
0S$
0V$
09
0A
0I
0Q
0_
0g
0o
0w
0+"
03"
0;"
0C"
0Q"
0Y"
0a"
0i"
0!#
0)#
01#
09#
0G#
0O#
0W#
0_#
0q#
0y#
0#$
0+$
09$
0A$
0I$
0Q$
b0 3
b0 Y
b0 %"
b0 K"
b0 y"
b0 A#
b0 k#
b0 3$
b0 /
b0 !"
b0 u"
b0 g#
b0 +
b0 q"
b0 $
b0 '
#3
b0 !
b0 (
b0 ,
b0 0
b0 4
0:
0%
#4
1:
1B
1J
b1111 4
1R
1`
1h
1p
b11111111 0
b1111 Z
1x
1,"
14"
1<"
b1111 &"
1D"
1R"
1Z"
1b"
b1111111111111111 ,
b11111111 ""
b1111 L"
1j"
1"#
1*#
12#
b1111 z"
1:#
1H#
1P#
1X#
b11111111 v"
b1111 B#
1`#
1r#
1z#
1$$
b1111 l#
1,$
1:$
1B$
1J$
b11111111111111111111111111111111 !
b11111111111111111111111111111111 (
b1111111111111111 r"
b11111111 h#
b1111 4$
1R$
1;
1C
1K
1S
1a
1i
1q
1y
1-"
15"
1="
1E"
1S"
1["
1c"
1k"
1##
1+#
13#
1;#
1I#
1Q#
1Y#
1a#
1s#
1{#
1%$
1-$
1;$
1C$
1K$
1S$
18
1@
1H
1P
1^
1f
1n
1v
1*"
12"
1:"
1B"
1P"
1X"
1`"
1h"
1~"
1(#
10#
18#
1F#
1N#
1V#
1^#
1p#
1x#
1"$
1*$
18$
1@$
1H$
1P$
b1111 2
b1111 X
b1111 $"
b1111 J"
b1111 x"
b1111 @#
b1111 j#
b1111 2$
b11111111 .
b11111111 ~
b11111111 t"
b11111111 f#
b1111111111111111 *
b1111111111111111 p"
b11111111111111111111111111111111 #
b11111111111111111111111111111111 &
#5
1E
1F
1M
1N
1U
1V
1c
1d
1k
1l
1s
1t
1{
1|
1/"
10"
17"
18"
1?"
1@"
1G"
1H"
1U"
1V"
1]"
1^"
1e"
1f"
1m"
1n"
1%#
1&#
1-#
1.#
15#
16#
1=#
1>#
1K#
1L#
1S#
1T#
1[#
1\#
1c#
1d#
1u#
1v#
1}#
1~#
1'$
1($
1/$
10$
1=$
1>$
1E$
1F$
1M$
1N$
1U$
1V$
17
16
15
11
1]
1\
1[
1-
1)"
1("
1'"
1#"
1O"
1N"
1M"
1)
1}"
1|"
1{"
1w"
1E#
1D#
1C#
1s"
1o#
1n#
1m#
1i#
17$
16$
15$
1"
0:
1?
1B
1G
1J
1O
b1110 4
1R
1W
1`
1e
1h
1m
1p
1u
b11111110 0
b1111 Z
1x
1}
1,"
11"
14"
19"
1<"
1A"
b1111 &"
1D"
1I"
1R"
1W"
1Z"
1_"
1b"
1g"
b1111111111111110 ,
b11111111 ""
b1111 L"
1j"
1o"
1"#
1'#
1*#
1/#
12#
17#
b1111 z"
1:#
1?#
1H#
1M#
1P#
1U#
1X#
1]#
b11111111 v"
b1111 B#
1`#
1e#
1r#
1w#
1z#
1!$
1$$
1)$
b1111 l#
1,$
11$
1:$
1?$
1B$
1G$
1J$
1O$
b11111111111111111111111111111110 !
b11111111111111111111111111111110 (
b1111111111111111 r"
b11111111 h#
b1111 4$
1R$
1W$
0;
1<
0C
1D
0K
1L
0S
1T
0a
1b
0i
1j
0q
1r
0y
1z
0-"
1."
05"
16"
0="
1>"
0E"
1F"
0S"
1T"
0["
1\"
0c"
1d"
0k"
1l"
0##
1$#
0+#
1,#
03#
14#
0;#
1<#
0I#
1J#
0Q#
1R#
0Y#
1Z#
0a#
1b#
0s#
1t#
0{#
1|#
0%$
1&$
0-$
1.$
0;$
1<$
0C$
1D$
0K$
1L$
0S$
1T$
19
1A
1I
1Q
1_
1g
1o
1w
1+"
13"
1;"
1C"
1Q"
1Y"
1a"
1i"
1!#
1)#
11#
19#
1G#
1O#
1W#
1_#
1q#
1y#
1#$
1+$
19$
1A$
1I$
1Q$
b1111 3
b1111 Y
b1111 %"
b1111 K"
b1111 y"
b1111 A#
b1111 k#
b1111 3$
b11111111 /
b11111111 !"
b11111111 u"
b11111111 g#
b1111111111111111 +
b1111111111111111 q"
b11111111111111111111111111111111 $
b11111111111111111111111111111111 '
#6
b11111111111111111111111111111111 !
b11111111111111111111111111111111 (
b1111111111111111 ,
b11111111 0
b1111 4
1:
1=
1>
1%
#7
0:
b1010 4
0J
0`
b10101010 0
b1010 Z
0p
0,"
b1010 &"
0<"
0R"
b1010101010101010 ,
b10101010 ""
b1010 L"
0b"
0"#
b1010 z"
02#
0H#
b10101010 v"
b1010 B#
0X#
0r#
b1010 l#
0$$
0:$
b10101010101010101010101010101010 !
b10101010101010101010101010101010 (
b1010101010101010 r"
b10101010 h#
b1010 4$
0J$
1;
0<
0>
1K
0L
0N
1a
0b
0d
1q
0r
0t
1-"
0."
00"
1="
0>"
0@"
1S"
0T"
0V"
1c"
0d"
0f"
1##
0$#
0&#
13#
04#
06#
1I#
0J#
0L#
1Y#
0Z#
0\#
1s#
0t#
0v#
1%$
0&$
0($
1;$
0<$
0>$
1K$
0L$
0N$
09
0I
0_
0o
0+"
0;"
0Q"
0a"
0!#
01#
0G#
0W#
0q#
0#$
09$
0I$
b1010 3
b1010 Y
b1010 %"
b1010 K"
b1010 y"
b1010 A#
b1010 k#
b1010 3$
b10101010 /
b10101010 !"
b10101010 u"
b10101010 g#
b1010101010101010 +
b1010101010101010 q"
b10101010101010101010101010101010 $
b10101010101010101010101010101010 '
